cutclip.py
cutclip-0.1.0.dist-info/METADATA
cutclip-0.1.0.dist-info/WHEEL
cutclip-0.1.0.dist-info/entry_points.txt
cutclip-0.1.0.dist-info/RECORD
