Metadata-Version: 2.1
Name: cutclip
Version: 0.1.0
Summary: cuts up a clip
Author: Sam Lavigne
Author-email: splavigne@gmail.com
Requires-Python: >=3.11,<4.0
Classifier: Programming Language :: Python :: 3
Classifier: Programming Language :: Python :: 3.11
Requires-Dist: moviepy (>=1.0.3,<2.0.0)
